{
  "type": "FeatureCollection",
  "features": [
    {
      "type": "Feature",
      "geometry": {
        "type": "Point",
        "coordinates": [
          19.033542,
          50.255506
        ]
      },
      "properties": {
        "name": "Politechnika Slaska",
        "temperature": 21.37,
        "pressure": 1020
      }
    }
  ]
}