{
  "type": "FeatureCollection",
  "features": [
    {
      "type": "Feature",
      "geometry": {
        "type": "Point",
        "coordinates": [
          19.033542,
          50.255506
        ]
      },
      "properties": {
        "name": "Politechnika Slaska",
        "temperature": "21.37째C",
        "pressure": "1020 hPa",
        "humidity": "70%",
        "rainfall": "Mocno pada",
        "windspeed": "100 km/h"
      }
    },
    {
      "type": "Feature",
      "geometry": {
        "type": "Point",
        "coordinates": [
          19.02674,
          50.26628
        ]
      },
      "properties": {
        "name": "Abcabc",
        "temperature": "41째C",
        "pressure": "1022 hPa",
        "humidity": "31%",
        "rainfall": "Nie pada",
        "windspeed": "31 km/h"
      }
    },
    {
      "type": "Feature",
      "geometry": {
        "type": "Point",
        "coordinates": [
          19.034769,
          50.256130
        ]
      },
      "properties": {
        "name": "wadsaeqw",
        "temperature": "29째C",
        "pressure": "1020 hPa",
        "humidity": "80%",
        "rainfall": "pada",
        "windspeed": "21 km/h"
      }
    },
    {
      "type": "Feature",
      "geometry": {
        "type": "Point",
        "coordinates": [
          19.01434,
          50.26198 
        ]
      },
      "properties": {
        "name": "ASdadasd",
        "temperature": "21째C",
        "pressure": "1010 hPa",
        "humidity": "50%",
        "rainfall": "Pada",
        "windspeed": "51 km/h"
      }
    }
  ]
}